{
  "type": "Feature",
  "properties": {
    "iso:country":"HR",
    "sg:address":"Slavonska avenija 26/4",
    "sg:city":"Zagreb",
    "sg:classifiers":[
        {
            "category":"Professional",
            "subcategory":"Computer Services",
            "type":"Services"
        }
    ],
    "sg:postcode":"10000",
    "sg:tags":[
        "design",
        "household-appliances"
    ],
    "sg:website":"http://www.gorenje.com/",
    "wof:name":"Gorenje",
    "wof:placetype":"venue"
},
  "geometry": {"coordinates":[15.961251,45.793899],"type":"Point"}
}